moleview/__init__.py
moleview/src/__init__.py
moleview/src/atom.py
moleview/src/draw.py
moleview/src/moleview.py
moleview-1.1.dist-info/LICENSE
moleview-1.1.dist-info/METADATA
moleview-1.1.dist-info/WHEEL
moleview-1.1.dist-info/entry_points.txt
moleview-1.1.dist-info/top_level.txt
moleview-1.1.dist-info/RECORD
