Metadata-Version: 2.1
Name: moleview
Version: 1.1
Summary: MoleView: view your molecule anywhere and anytime.
Home-page: https://github.com/moleview/moleview
Author: Rangsiman Ketkaew
Author-email: rangsiman1993@gmail.com
License: UNKNOWN
Download-URL: https://github.com/moleview/moleview/releases
Keywords: chemistry,computational chemistry,crystallography,Molecular visualization
Platform: UNKNOWN
Classifier: Programming Language :: Python :: 3
Classifier: License :: OSI Approved :: MIT License
Classifier: Operating System :: OS Independent
Requires-Python: >=3.6
License-File: LICENSE
